huaweicloudsdkddm/__init__.py
huaweicloudsdkddm/v1/__init__.py
huaweicloudsdkddm/v1/ddm_async_client.py
huaweicloudsdkddm/v1/ddm_client.py
huaweicloudsdkddm/v1/model/__init__.py
huaweicloudsdkddm/v1/model/action_info.py
huaweicloudsdkddm/v1/model/admin_user_info_req.py
huaweicloudsdkddm/v1/model/api_version.py
huaweicloudsdkddm/v1/model/applicable_instance.py
huaweicloudsdkddm/v1/model/apply_history.py
huaweicloudsdkddm/v1/model/available_dn_instance.py
huaweicloudsdkddm/v1/model/available_zone.py
huaweicloudsdkddm/v1/model/backup_info.py
huaweicloudsdkddm/v1/model/batch_delete_nodes_request.py
huaweicloudsdkddm/v1/model/batch_delete_nodes_response.py
huaweicloudsdkddm/v1/model/bind_eip_open_request.py
huaweicloudsdkddm/v1/model/bind_eip_request.py
huaweicloudsdkddm/v1/model/bind_eip_response.py
huaweicloudsdkddm/v1/model/cancel_migration_request.py
huaweicloudsdkddm/v1/model/cancel_migration_response.py
huaweicloudsdkddm/v1/model/change_database_version_request.py
huaweicloudsdkddm/v1/model/change_database_version_response.py
huaweicloudsdkddm/v1/model/change_strategy_request.py
huaweicloudsdkddm/v1/model/change_strategy_response.py
huaweicloudsdkddm/v1/model/check_data_node_connection_v0_v3_request.py
huaweicloudsdkddm/v1/model/check_data_node_connection_v0_v3_response.py
huaweicloudsdkddm/v1/model/check_migrate_logic_db_request.py
huaweicloudsdkddm/v1/model/check_migrate_logic_db_response.py
huaweicloudsdkddm/v1/model/check_preliminary_results_request.py
huaweicloudsdkddm/v1/model/check_preliminary_results_response.py
huaweicloudsdkddm/v1/model/check_rds_connection_resq_vo.py
huaweicloudsdkddm/v1/model/clean_migration_request.py
huaweicloudsdkddm/v1/model/clean_migration_response.py
huaweicloudsdkddm/v1/model/compare_parameter_groups_request.py
huaweicloudsdkddm/v1/model/compare_parameter_groups_response.py
huaweicloudsdkddm/v1/model/compute_flavor_groups_info.py
huaweicloudsdkddm/v1/model/compute_flavors.py
huaweicloudsdkddm-3.1.184.dist-info/METADATA
huaweicloudsdkddm-3.1.184.dist-info/WHEEL
huaweicloudsdkddm-3.1.184.dist-info/licenses/LICENSE
huaweicloudsdkddm-3.1.184.dist-info/RECORD
